djangocms_link_manager/__init__.py
djangocms_link_manager/apps.py
djangocms_link_manager/link_manager.py
djangocms_link_manager/link_manager_pool.py
djangocms_link_manager/link_managers/__init__.py
djangocms_link_manager/link_managers/bootstrap3_button_cmsplugin.py
djangocms_link_manager/link_managers/cmsplugin_link.py
djangocms_link_manager/management/__init__.py
djangocms_link_manager/management/commands/__init__.py
djangocms_link_manager/management/commands/check_links.py
djangocms_link_manager/templates/djangocms_link_manager/text_only.rst
djangocms_link_manager/tests/__init__.py
djangocms_link_manager/tests/test_link_manager.py
djangocms_link_manager/tests/test_link_manager_pool.py
djangocms_link_manager-0.2.1.dist-info/DESCRIPTION.rst
djangocms_link_manager-0.2.1.dist-info/METADATA
djangocms_link_manager-0.2.1.dist-info/RECORD
djangocms_link_manager-0.2.1.dist-info/WHEEL
djangocms_link_manager-0.2.1.dist-info/metadata.json
djangocms_link_manager-0.2.1.dist-info/top_level.txt
