Metadata-Version: 2.0
Name: djangocms-link-manager
Version: 0.2.1
Summary: An extensible means of checking for broken links in virtually any django CMS plugin.
Home-page: https://github.com/divio/djangocms-link-manager/
Author: Divio
Author-email: info@divio.com
License: LICENSE.txt
Platform: OS Independent
Classifier: Development Status :: 5 - Production/Stable
Classifier: Environment :: Web Environment
Classifier: Framework :: Django
Classifier: Framework :: Django :: 1.8
Classifier: Framework :: Django :: 1.9
Classifier: Intended Audience :: Developers
Classifier: License :: OSI Approved :: BSD License
Classifier: Operating System :: OS Independent
Classifier: Programming Language :: Python
Classifier: Programming Language :: Python :: 2.7
Classifier: Programming Language :: Python :: 3.3
Classifier: Programming Language :: Python :: 3.4
Classifier: Programming Language :: Python :: 3.5
Classifier: Topic :: Software Development
Classifier: Topic :: Software Development :: Libraries :: Application Frameworks
Requires-Dist: attrs
Requires-Dist: django (>=1.8.0)
Requires-Dist: django-cms (>=3.0)
Requires-Dist: phonenumberslite (>=7.4,<8.0)
